zsqlite/__cls_aide_rst_base__.py
zsqlite/__cls_aide_sql_sqlite__.py
zsqlite/__cls_sqlite_conn__.py
zsqlite/__init__.py
zsqlite-3.2.dist-info/LICENSE
zsqlite-3.2.dist-info/METADATA
zsqlite-3.2.dist-info/WHEEL
zsqlite-3.2.dist-info/top_level.txt
zsqlite-3.2.dist-info/RECORD
