Metadata-Version: 2.1
Name: zsqlite
Version: 3.2
Summary: A useless database connection based on sqlite3
Home-page: https://github.com/zhstack/zsqlite.git
Author: zhstack
Author-email: zhstack@163.com
License: MIT
Keywords: zsqlite
License-File: LICENSE
